bento_lib/__init__.py
bento_lib/_internal.py
bento_lib/apps/__init__.py
bento_lib/apps/fastapi.py
bento_lib/auth/__init__.py
bento_lib/auth/exceptions.py
bento_lib/auth/helpers.py
bento_lib/auth/middleware/__init__.py
bento_lib/auth/middleware/base.py
bento_lib/auth/middleware/django.py
bento_lib/auth/middleware/fastapi.py
bento_lib/auth/middleware/flask.py
bento_lib/auth/middleware/mark_authz_done_mixin.py
bento_lib/auth/permissions.py
bento_lib/auth/resources.py
bento_lib/auth/types.py
bento_lib/config/__init__.py
bento_lib/config/pydantic.py
bento_lib/db/__init__.py
bento_lib/db/pg_async.py
bento_lib/discovery/__init__.py
bento_lib/discovery/exceptions.py
bento_lib/discovery/helpers.py
bento_lib/discovery/models/__init__.py
bento_lib/discovery/models/_internal.py
bento_lib/discovery/models/config.py
bento_lib/discovery/models/fields.py
bento_lib/discovery/models/overview.py
bento_lib/discovery/models/search.py
bento_lib/discovery/types.py
bento_lib/drs/__init__.py
bento_lib/drs/exceptions.py
bento_lib/drs/resolver.py
bento_lib/drs/utils.py
bento_lib/events/__init__.py
bento_lib/events/_event_bus.py
bento_lib/events/notifications.py
bento_lib/events/types.py
bento_lib/logging/__init__.py
bento_lib/logging/structured/__init__.py
bento_lib/logging/structured/common.py
bento_lib/logging/structured/configure.py
bento_lib/logging/structured/django.py
bento_lib/logging/structured/fastapi.py
bento_lib/logging/types.py
bento_lib/ontologies/__init__.py
bento_lib/ontologies/common_classes.py
bento_lib/ontologies/common_resources.py
bento_lib/ontologies/models.py
bento_lib/ontologies/types.py
bento_lib/responses/__init__.py
bento_lib/responses/errors.py
bento_lib/responses/fastapi_errors.py
bento_lib/responses/flask_errors.py
bento_lib/schemas/__init__.py
bento_lib/schemas/_utils.py
bento_lib/schemas/bento.py
bento_lib/schemas/bento_data_use.schema.json
bento_lib/schemas/ga4gh.py
bento_lib/schemas/ga4gh_service_info.schema.json
bento_lib/search/__init__.py
bento_lib-14.1.2.dist-info/METADATA
bento_lib-14.1.2.dist-info/WHEEL
bento_lib-14.1.2.dist-info/licenses/LICENSE
bento_lib-14.1.2.dist-info/RECORD
