Metadata-Version: 2.4
Name: bento-lib
Version: 14.1.2
Summary: A set of common utilities and helpers for Bento platform services.
License: LGPL-3.0
License-File: LICENSE
Author: David Lougheed
Author-email: david.lougheed@mail.mcgill.ca
Requires-Python: >=3.12,<4.0
Classifier: License :: OSI Approved :: GNU Lesser General Public License v3 (LGPLv3)
Classifier: Operating System :: OS Independent
Classifier: Programming Language :: Python :: 3
Classifier: Programming Language :: Python :: 3.12
Classifier: Programming Language :: Python :: 3.13
Classifier: Programming Language :: Python :: 3.14
Provides-Extra: asyncpg
Provides-Extra: django
Provides-Extra: fastapi
Provides-Extra: flask
Requires-Dist: aiofiles (>=24.1.0,<26)
Requires-Dist: aiohttp (>=3.10.10,<4)
Requires-Dist: asyncpg (>=0.29.0,<0.32.0) ; extra == "asyncpg"
Requires-Dist: django (>=5.1.8,<5.3) ; extra == "django"
Requires-Dist: djangorestframework (>=3.16.0,<3.17) ; extra == "django"
Requires-Dist: fastapi (>=0.115.12,<0.129) ; extra == "fastapi"
Requires-Dist: flask (>=3.0.3,<4) ; extra == "flask"
Requires-Dist: geojson-pydantic (>=2.0.0,<3.0.0)
Requires-Dist: jsonschema (>=4.23.0,<5)
Requires-Dist: psycopg2-binary (>=2.9.9,<3.0)
Requires-Dist: pydantic (>=2.11.3,<3)
Requires-Dist: pydantic-settings (>=2.8.1)
Requires-Dist: redis (>=5.2.1,<8)
Requires-Dist: requests (>=2.32.3,<3)
Requires-Dist: rich (>=14.0.0,<15)
Requires-Dist: structlog (>=25.2.0,<26)
Requires-Dist: uvicorn ; extra == "fastapi"
Requires-Dist: werkzeug (>=3.0.6,<4)
Project-URL: Repository, https://github.com/bento-platform/bento_lib
